itfit/__init__.py
itfit/fitter_app.py
itfit/function_constructor.py
itfit/data/__init__.py
itfit/data/data_classes.py
itfit/data_selectors/__init__.py
itfit/data_selectors/lasso.py
itfit/fit_functions/__init__.py
itfit/fit_functions/common/__init__.py
itfit/fit_functions/common/function_container.py
itfit/fit_functions/common/generic_fitter.py
itfit/fit_functions/cosine/__init__.py
itfit/fit_functions/cosine/cosine.py
itfit/fit_functions/exponential/__init__.py
itfit/fit_functions/exponential/exponential.py
itfit/fit_functions/gaussian/__init__.py
itfit/fit_functions/gaussian/gaussian.py
itfit/fit_functions/linear/__init__.py
itfit/fit_functions/linear/linear.py
itfit/fit_functions/lorentzian/__init__.py
itfit/fit_functions/lorentzian/lorentzian.py
itfit/fit_functions/quadratic/__init__.py
itfit/fit_functions/quadratic/quadratic.py
itfit/fit_functions/sine/__init__.py
itfit/fit_functions/sine/sine.py
itfit/plot/__init__.py
itfit/plot/builder.py
itfit/plot/labels.py
itfit/plot/spines.py
itfit/utils/__init__.py
itfit/utils/blit_manager.py
itfit/utils/collection.py
itfit/utils/fit_container.py
itfit/utils/fit_selector.py
itfit/utils/point.py
itfit-0.1.0.dist-info/LICENSE
itfit-0.1.0.dist-info/METADATA
itfit-0.1.0.dist-info/WHEEL
itfit-0.1.0.dist-info/top_level.txt
itfit-0.1.0.dist-info/RECORD
